mitfat/_Lib.py
mitfat/__init__.py
mitfat/_basics.py
mitfat/_decompose.py
mitfat/_detrending.py
mitfat/_plotting.py
mitfat/_private.py
mitfat/_shapes.py
mitfat/bplots.py
mitfat/clustering.py
mitfat/collections.py
mitfat/file_io.py
mitfat/flags.py
mitfat/fmri_dataset.py
mitfat-0.2.0.dist-info/LICENSE
mitfat-0.2.0.dist-info/METADATA
mitfat-0.2.0.dist-info/WHEEL
mitfat-0.2.0.dist-info/top_level.txt
mitfat-0.2.0.dist-info/RECORD
