Metadata-Version: 2.1
Name: mitfat
Version: 0.2.0
Summary: A Python-based Scikit-Learn-friendly fMRI Analysis Tool, Made in Tuebingen.
Home-page: https://github.com/vahid-sb/MiTfAT
Author: Vahid Samadi Bokharaie
Author-email: vahid.bokharaie@protonmail.com
License: GNU Version 3
Platform: UNKNOWN
Classifier: Development Status :: 4 - Beta
Classifier: License :: OSI Approved :: GNU General Public License v3 (GPLv3)
Classifier: Programming Language :: Python
Classifier: Programming Language :: Python :: 3.7
Classifier: Programming Language :: Python :: 3.8
Requires-Dist: pandas
Requires-Dist: numpy
Requires-Dist: scipy
Requires-Dist: matplotlib
Requires-Dist: nibabel
Requires-Dist: nilearn
Requires-Dist: pathlib
Requires-Dist: seaborn
Requires-Dist: openpyxl
